smoothnlp/__init__.py
smoothnlp/configurations.py
smoothnlp/nlp.py
smoothnlp/pipeline.py
smoothnlp/server.py
smoothnlp/algorithm/__init__.py
smoothnlp/algorithm/keyword/__init__.py
smoothnlp/algorithm/kg/__init__.py
smoothnlp/algorithm/kg/attr.py
smoothnlp/algorithm/kg/entity.py
smoothnlp/algorithm/kg/event.py
smoothnlp/algorithm/kg/helper.py
smoothnlp/algorithm/kg/phrase.py
smoothnlp/algorithm/phrase/__init__.py
smoothnlp/algorithm/phrase/ngram_utils.py
smoothnlp/algorithm/phrase/phrase_extraction.py
smoothnlp/jvm/__init__.py
smoothnlp/jvm/static.py
smoothnlp/server/__init__.py
smoothnlp/static/__init__.py
smoothnlp/static/jvm.py
smoothnlp/utils/__init__.py
SmoothNLP-0.4.0.dist-info/LICENSE
SmoothNLP-0.4.0.dist-info/METADATA
SmoothNLP-0.4.0.dist-info/PKG-INFO.sync-conflict-20190827-104643-OUK2C2L
SmoothNLP-0.4.0.dist-info/SOURCES.sync-conflict-20190827-104643-OUK2C2L.txt
SmoothNLP-0.4.0.dist-info/SOURCES.sync-conflict-20190830-174718-OUK2C2L.txt
SmoothNLP-0.4.0.dist-info/SOURCES.sync-conflict-20190830-174918-OUK2C2L.txt
SmoothNLP-0.4.0.dist-info/SOURCES.sync-conflict-20190830-175129-OUK2C2L.txt
SmoothNLP-0.4.0.dist-info/SOURCES.sync-conflict-20190830-175649-OUK2C2L.txt
SmoothNLP-0.4.0.dist-info/SOURCES.sync-conflict-20190830-180129-OUK2C2L.txt
SmoothNLP-0.4.0.dist-info/WHEEL
SmoothNLP-0.4.0.dist-info/requires.sync-conflict-20190827-104643-OUK2C2L.txt
SmoothNLP-0.4.0.dist-info/requires.sync-conflict-20190830-174708-OUK2C2L.txt
SmoothNLP-0.4.0.dist-info/top_level.txt
SmoothNLP-0.4.0.dist-info/RECORD
