Metadata-Version: 2.1
Name: SmoothNLP
Version: 0.4.0
Summary: Python Package for SmoothNLP
Home-page: https://github.com/smoothnlp/SmoothNLP
Author: SmoothNLP Oraganization
Author-email: contact@smoothnlp.com
License: UNKNOWN
Keywords: NLP,Python,SmoothNLP,Natural Language Processing,Knowledge Graph Extraction
Platform: UNKNOWN
Classifier: Programming Language :: Python :: 3
Classifier: License :: OSI Approved :: MIT License
Classifier: Operating System :: OS Independent
Requires-Dist: numpy
Requires-Dist: requests
Requires-Dist: pygtrie
Requires-Dist: networkx
